merrygo/__init__.py
merrygo/main.py
merrygo-0.0.4.dist-info/LICENSE
merrygo-0.0.4.dist-info/METADATA
merrygo-0.0.4.dist-info/WHEEL
merrygo-0.0.4.dist-info/entry_points.txt
merrygo-0.0.4.dist-info/top_level.txt
merrygo-0.0.4.dist-info/RECORD
