Metadata-Version: 2.1
Name: merrygo
Version: 0.0.4
Summary: Person Python project manager
Author-email: Manuel Šarić <manujelko@gmail.com>
License: MIT License
Project-URL: Homepage, https://github.com/manujelko/merrygo
Project-URL: Issues, https://github.com/manujelko/merrygo/issues
Classifier: Operating System :: Unix
Classifier: Intended Audience :: Developers
Classifier: License :: OSI Approved :: MIT License
Classifier: Programming Language :: Python :: 3
Classifier: Programming Language :: Python :: 3.8
Classifier: Programming Language :: Python :: 3.9
Classifier: Programming Language :: Python :: 3.10
Classifier: Programming Language :: Python :: 3.11
Classifier: Programming Language :: Python :: 3.12
Requires-Python: >=3.8
License-File: LICENSE
Requires-Dist: rich
Requires-Dist: typer
Provides-Extra: dev
Requires-Dist: bpython ; extra == 'dev'
Requires-Dist: mypy >=0.3.2 ; extra == 'dev'
Requires-Dist: pdbpp ; extra == 'dev'
Requires-Dist: ruff ; extra == 'dev'
